describe_dataset/__init__.py
describe_dataset/describer.py
describe_dataset-0.1.2.dist-info/METADATA
describe_dataset-0.1.2.dist-info/WHEEL
describe_dataset-0.1.2.dist-info/top_level.txt
describe_dataset-0.1.2.dist-info/RECORD
