Metadata-Version: 2.1
Name: describe-dataset
Version: 0.1.2
Summary: Add your description here
Requires-Python: >=3.9.18
Requires-Dist: fire>=0.7.0
Requires-Dist: pillow>=11.1.0
Requires-Dist: pyyaml>=6.0.2
